<?xml version="1.0"?>
<objects>
<!-- ('', 'zport', 'dmd', 'Devices', 'Server', 'Linux', 'rrdTemplates', 'Varnish3') -->
<object id='/zport/dmd/Devices/Server/Linux/rrdTemplates/Varnish3' module='Products.ZenModel.RRDTemplate' class='RRDTemplate'>
<property type="string" id="targetPythonClass" mode="w" >
Products.ZenModel.Device
</property>
<tomanycont id='datasources'>
<object id='Varnish3Stats' module='Products.ZenModel.BasicDataSource' class='BasicDataSource'>
<property select_variable="sourcetypes" type="selection" id="sourcetype" mode="w" >
COMMAND
</property>
<property type="boolean" id="enabled" mode="w" >
True
</property>
<property type="string" id="eventClass" mode="w" >
/Cmd/Fail
</property>
<property type="int" id="severity" mode="w" >
3
</property>
<property type="string" id="commandTemplate" mode="w" >
/usr/bin/varnishstat -x
</property>
<property type="int" id="cycletime" mode="w" >
300
</property>
<property type="boolean" id="usessh" mode="w" >
True
</property>
<property type="string" id="parser" mode="w" >
ZenPacks.community.Varnish3.parsers.VarnishStat
</property>
<tomanycont id='datapoints'>
<object id='backend_busy' module='Products.ZenModel.RRDDataPoint' class='RRDDataPoint'>
<property select_variable="rrdtypes" type="selection" id="rrdtype" mode="w" >
DERIVE
</property>
<property type="boolean" id="isrow" mode="w" >
True
</property>
</object>
<object id='backend_conn' module='Products.ZenModel.RRDDataPoint' class='RRDDataPoint'>
<property select_variable="rrdtypes" type="selection" id="rrdtype" mode="w" >
DERIVE
</property>
<property type="boolean" id="isrow" mode="w" >
True
</property>
</object>
<object id='backend_fail' module='Products.ZenModel.RRDDataPoint' class='RRDDataPoint'>
<property select_variable="rrdtypes" type="selection" id="rrdtype" mode="w" >
DERIVE
</property>
<property type="boolean" id="isrow" mode="w" >
True
</property>
</object>
<object id='backend_recycle' module='Products.ZenModel.RRDDataPoint' class='RRDDataPoint'>
<property select_variable="rrdtypes" type="selection" id="rrdtype" mode="w" >
DERIVE
</property>
<property type="boolean" id="isrow" mode="w" >
True
</property>
</object>
<object id='backend_req' module='Products.ZenModel.RRDDataPoint' class='RRDDataPoint'>
<property select_variable="rrdtypes" type="selection" id="rrdtype" mode="w" >
DERIVE
</property>
<property type="boolean" id="isrow" mode="w" >
True
</property>
</object>
<object id='backend_retry' module='Products.ZenModel.RRDDataPoint' class='RRDDataPoint'>
<property select_variable="rrdtypes" type="selection" id="rrdtype" mode="w" >
DERIVE
</property>
<property type="boolean" id="isrow" mode="w" >
True
</property>
</object>
<object id='backend_reuse' module='Products.ZenModel.RRDDataPoint' class='RRDDataPoint'>
<property select_variable="rrdtypes" type="selection" id="rrdtype" mode="w" >
DERIVE
</property>
<property type="boolean" id="isrow" mode="w" >
True
</property>
</object>
<object id='backend_toolate' module='Products.ZenModel.RRDDataPoint' class='RRDDataPoint'>
<property select_variable="rrdtypes" type="selection" id="rrdtype" mode="w" >
DERIVE
</property>
<property type="boolean" id="isrow" mode="w" >
True
</property>
</object>
<object id='backend_unhealthy' module='Products.ZenModel.RRDDataPoint' class='RRDDataPoint'>
<property select_variable="rrdtypes" type="selection" id="rrdtype" mode="w" >
DERIVE
</property>
<property type="boolean" id="isrow" mode="w" >
True
</property>
</object>
<object id='cache_hit' module='Products.ZenModel.RRDDataPoint' class='RRDDataPoint'>
<property select_variable="rrdtypes" type="selection" id="rrdtype" mode="w" >
DERIVE
</property>
<property type="boolean" id="isrow" mode="w" >
True
</property>
</object>
<object id='cache_hitpass' module='Products.ZenModel.RRDDataPoint' class='RRDDataPoint'>
<property select_variable="rrdtypes" type="selection" id="rrdtype" mode="w" >
DERIVE
</property>
<property type="boolean" id="isrow" mode="w" >
True
</property>
</object>
<object id='cache_miss' module='Products.ZenModel.RRDDataPoint' class='RRDDataPoint'>
<property select_variable="rrdtypes" type="selection" id="rrdtype" mode="w" >
DERIVE
</property>
<property type="boolean" id="isrow" mode="w" >
True
</property>
</object>
<object id='client_conn' module='Products.ZenModel.RRDDataPoint' class='RRDDataPoint'>
<property select_variable="rrdtypes" type="selection" id="rrdtype" mode="w" >
DERIVE
</property>
<property type="boolean" id="isrow" mode="w" >
True
</property>
</object>
<object id='client_req' module='Products.ZenModel.RRDDataPoint' class='RRDDataPoint'>
<property select_variable="rrdtypes" type="selection" id="rrdtype" mode="w" >
DERIVE
</property>
<property type="boolean" id="isrow" mode="w" >
True
</property>
</object>
<object id='esi_errors' module='Products.ZenModel.RRDDataPoint' class='RRDDataPoint'>
<property select_variable="rrdtypes" type="selection" id="rrdtype" mode="w" >
DERIVE
</property>
<property type="boolean" id="isrow" mode="w" >
True
</property>
</object>
<object id='esi_warnings' module='Products.ZenModel.RRDDataPoint' class='RRDDataPoint'>
<property select_variable="rrdtypes" type="selection" id="rrdtype" mode="w" >
DERIVE
</property>
<property type="boolean" id="isrow" mode="w" >
True
</property>
</object>
<object id='fetch_head' module='Products.ZenModel.RRDDataPoint' class='RRDDataPoint'>
<property select_variable="rrdtypes" type="selection" id="rrdtype" mode="w" >
DERIVE
</property>
<property type="boolean" id="isrow" mode="w" >
True
</property>
</object>
<object id='n_backend' module='Products.ZenModel.RRDDataPoint' class='RRDDataPoint'>
<property select_variable="rrdtypes" type="selection" id="rrdtype" mode="w" >
GAUGE
</property>
<property type="boolean" id="isrow" mode="w" >
True
</property>
</object>
<object id='n_expired' module='Products.ZenModel.RRDDataPoint' class='RRDDataPoint'>
<property select_variable="rrdtypes" type="selection" id="rrdtype" mode="w" >
DERIVE
</property>
<property type="boolean" id="isrow" mode="w" >
True
</property>
</object>
<object id='n_gunzip' module='Products.ZenModel.RRDDataPoint' class='RRDDataPoint'>
<property select_variable="rrdtypes" type="selection" id="rrdtype" mode="w" >
DERIVE
</property>
<property type="boolean" id="isrow" mode="w" >
True
</property>
</object>
<object id='n_gzip' module='Products.ZenModel.RRDDataPoint' class='RRDDataPoint'>
<property select_variable="rrdtypes" type="selection" id="rrdtype" mode="w" >
DERIVE
</property>
<property type="boolean" id="isrow" mode="w" >
True
</property>
</object>
<object id='n_wrk' module='Products.ZenModel.RRDDataPoint' class='RRDDataPoint'>
<property select_variable="rrdtypes" type="selection" id="rrdtype" mode="w" >
GAUGE
</property>
<property type="boolean" id="isrow" mode="w" >
True
</property>
</object>
<object id='n_wrk_create' module='Products.ZenModel.RRDDataPoint' class='RRDDataPoint'>
<property select_variable="rrdtypes" type="selection" id="rrdtype" mode="w" >
DERIVE
</property>
<property type="boolean" id="isrow" mode="w" >
True
</property>
</object>
<object id='n_wrk_lqueue' module='Products.ZenModel.RRDDataPoint' class='RRDDataPoint'>
<property select_variable="rrdtypes" type="selection" id="rrdtype" mode="w" >
GAUGE
</property>
<property type="boolean" id="isrow" mode="w" >
True
</property>
</object>
<object id='n_wrk_queued' module='Products.ZenModel.RRDDataPoint' class='RRDDataPoint'>
<property select_variable="rrdtypes" type="selection" id="rrdtype" mode="w" >
DERIVE
</property>
<property type="boolean" id="isrow" mode="w" >
True
</property>
</object>
<object id='s_fetch' module='Products.ZenModel.RRDDataPoint' class='RRDDataPoint'>
<property select_variable="rrdtypes" type="selection" id="rrdtype" mode="w" >
DERIVE
</property>
<property type="boolean" id="isrow" mode="w" >
True
</property>
</object>
<object id='s_pass' module='Products.ZenModel.RRDDataPoint' class='RRDDataPoint'>
<property select_variable="rrdtypes" type="selection" id="rrdtype" mode="w" >
DERIVE
</property>
<property type="boolean" id="isrow" mode="w" >
True
</property>
</object>
<object id='s_req' module='Products.ZenModel.RRDDataPoint' class='RRDDataPoint'>
<property select_variable="rrdtypes" type="selection" id="rrdtype" mode="w" >
DERIVE
</property>
<property type="boolean" id="isrow" mode="w" >
True
</property>
</object>
<object id='s_sess' module='Products.ZenModel.RRDDataPoint' class='RRDDataPoint'>
<property select_variable="rrdtypes" type="selection" id="rrdtype" mode="w" >
DERIVE
</property>
<property type="boolean" id="isrow" mode="w" >
True
</property>
</object>
<object id='uptime' module='Products.ZenModel.RRDDataPoint' class='RRDDataPoint'>
<property select_variable="rrdtypes" type="selection" id="rrdtype" mode="w" >
GAUGE
</property>
<property type="boolean" id="isrow" mode="w" >
True
</property>
</object>
</tomanycont>
</object>
</tomanycont>
<tomanycont id='graphDefs'>
<object id='Varnish 3 Cache Hits vs Misses' module='Products.ZenModel.GraphDefinition' class='GraphDefinition'>
<property type="int" id="height" mode="w" >
100
</property>
<property type="int" id="width" mode="w" >
500
</property>
<property type="boolean" id="log" mode="w" >
False
</property>
<property type="boolean" id="base" mode="w" >
False
</property>
<property type="int" id="miny" mode="w" >
-1
</property>
<property type="int" id="maxy" mode="w" >
-1
</property>
<property type="boolean" id="hasSummary" mode="w" >
True
</property>
<tomanycont id='graphPoints'>
<object id='cache_hit' module='Products.ZenModel.DataPointGraphPoint' class='DataPointGraphPoint'>
<property select_variable="lineTypes" type="selection" id="lineType" mode="w" >
LINE
</property>
<property type="long" id="lineWidth" mode="w" >
1
</property>
<property type="boolean" id="stacked" mode="w" >
False
</property>
<property type="string" id="format" mode="w" >
%5.2lf%s
</property>
<property type="string" id="legend" mode="w" >
${graphPoint/id}
</property>
<property type="long" id="limit" mode="w" >
-1
</property>
<property type="string" id="dpName" mode="w" >
Test_cache_hit
</property>
<property type="string" id="cFunc" mode="w" >
AVERAGE
</property>
</object>
<object id='cache_hitpass' module='Products.ZenModel.DataPointGraphPoint' class='DataPointGraphPoint'>
<property type="long" id="sequence" mode="w" >
2
</property>
<property select_variable="lineTypes" type="selection" id="lineType" mode="w" >
LINE
</property>
<property type="long" id="lineWidth" mode="w" >
1
</property>
<property type="boolean" id="stacked" mode="w" >
False
</property>
<property type="string" id="format" mode="w" >
%5.2lf%s
</property>
<property type="string" id="legend" mode="w" >
${graphPoint/id}
</property>
<property type="long" id="limit" mode="w" >
-1
</property>
<property type="string" id="dpName" mode="w" >
Varnish3Stats_cache_hitpass
</property>
<property type="string" id="cFunc" mode="w" >
AVERAGE
</property>
</object>
<object id='cache_miss' module='Products.ZenModel.DataPointGraphPoint' class='DataPointGraphPoint'>
<property type="long" id="sequence" mode="w" >
1
</property>
<property select_variable="lineTypes" type="selection" id="lineType" mode="w" >
LINE
</property>
<property type="long" id="lineWidth" mode="w" >
1
</property>
<property type="boolean" id="stacked" mode="w" >
False
</property>
<property type="string" id="format" mode="w" >
%5.2lf%s
</property>
<property type="string" id="legend" mode="w" >
${graphPoint/id}
</property>
<property type="long" id="limit" mode="w" >
-1
</property>
<property type="string" id="dpName" mode="w" >
Test_cache_miss
</property>
<property type="string" id="cFunc" mode="w" >
AVERAGE
</property>
</object>
</tomanycont>
</object>
<object id='Varnish3 Backend Too Late' module='Products.ZenModel.GraphDefinition' class='GraphDefinition'>
<property type="int" id="height" mode="w" >
100
</property>
<property type="int" id="width" mode="w" >
500
</property>
<property type="boolean" id="log" mode="w" >
False
</property>
<property type="boolean" id="base" mode="w" >
False
</property>
<property type="int" id="miny" mode="w" >
-1
</property>
<property type="int" id="maxy" mode="w" >
-1
</property>
<property type="boolean" id="hasSummary" mode="w" >
True
</property>
<property type="long" id="sequence" mode="w" >
1
</property>
<tomanycont id='graphPoints'>
<object id='backend_toolate' module='Products.ZenModel.DataPointGraphPoint' class='DataPointGraphPoint'>
<property select_variable="lineTypes" type="selection" id="lineType" mode="w" >
LINE
</property>
<property type="long" id="lineWidth" mode="w" >
1
</property>
<property type="boolean" id="stacked" mode="w" >
False
</property>
<property type="string" id="format" mode="w" >
%5.2lf%s
</property>
<property type="string" id="legend" mode="w" >
${graphPoint/id}
</property>
<property type="long" id="limit" mode="w" >
-1
</property>
<property type="string" id="dpName" mode="w" >
Varnish3Stats_backend_toolate
</property>
<property type="string" id="cFunc" mode="w" >
AVERAGE
</property>
</object>
</tomanycont>
</object>
<object id='Varnish3 Client Connections' module='Products.ZenModel.GraphDefinition' class='GraphDefinition'>
<property type="int" id="height" mode="w" >
100
</property>
<property type="int" id="width" mode="w" >
500
</property>
<property type="boolean" id="log" mode="w" >
False
</property>
<property type="boolean" id="base" mode="w" >
False
</property>
<property type="int" id="miny" mode="w" >
-1
</property>
<property type="int" id="maxy" mode="w" >
-1
</property>
<property type="boolean" id="hasSummary" mode="w" >
True
</property>
<property type="long" id="sequence" mode="w" >
3
</property>
<tomanycont id='graphPoints'>
<object id='client_conn' module='Products.ZenModel.DataPointGraphPoint' class='DataPointGraphPoint'>
<property select_variable="lineTypes" type="selection" id="lineType" mode="w" >
LINE
</property>
<property type="long" id="lineWidth" mode="w" >
1
</property>
<property type="boolean" id="stacked" mode="w" >
False
</property>
<property type="string" id="format" mode="w" >
%5.2lf%s
</property>
<property type="string" id="legend" mode="w" >
${graphPoint/id}
</property>
<property type="long" id="limit" mode="w" >
-1
</property>
<property type="string" id="dpName" mode="w" >
Varnish3Stats_client_conn
</property>
<property type="string" id="cFunc" mode="w" >
AVERAGE
</property>
</object>
</tomanycont>
</object>
<object id='Varnish3 Client Requests' module='Products.ZenModel.GraphDefinition' class='GraphDefinition'>
<property type="int" id="height" mode="w" >
100
</property>
<property type="int" id="width" mode="w" >
500
</property>
<property type="boolean" id="log" mode="w" >
False
</property>
<property type="boolean" id="base" mode="w" >
False
</property>
<property type="int" id="miny" mode="w" >
-1
</property>
<property type="int" id="maxy" mode="w" >
-1
</property>
<property type="boolean" id="hasSummary" mode="w" >
True
</property>
<property type="long" id="sequence" mode="w" >
2
</property>
<tomanycont id='graphPoints'>
<object id='client_req' module='Products.ZenModel.DataPointGraphPoint' class='DataPointGraphPoint'>
<property select_variable="lineTypes" type="selection" id="lineType" mode="w" >
LINE
</property>
<property type="long" id="lineWidth" mode="w" >
1
</property>
<property type="boolean" id="stacked" mode="w" >
False
</property>
<property type="string" id="format" mode="w" >
%5.2lf%s
</property>
<property type="string" id="legend" mode="w" >
${graphPoint/id}
</property>
<property type="long" id="limit" mode="w" >
-1
</property>
<property type="string" id="dpName" mode="w" >
Varnish3Stats_client_req
</property>
<property type="string" id="cFunc" mode="w" >
AVERAGE
</property>
</object>
</tomanycont>
</object>
<object id='Varnish3 Expired Objects' module='Products.ZenModel.GraphDefinition' class='GraphDefinition'>
<property type="int" id="height" mode="w" >
100
</property>
<property type="int" id="width" mode="w" >
500
</property>
<property type="boolean" id="log" mode="w" >
False
</property>
<property type="boolean" id="base" mode="w" >
False
</property>
<property type="int" id="miny" mode="w" >
-1
</property>
<property type="int" id="maxy" mode="w" >
-1
</property>
<property type="boolean" id="hasSummary" mode="w" >
True
</property>
<property type="long" id="sequence" mode="w" >
5
</property>
<tomanycont id='graphPoints'>
<object id='n_expired' module='Products.ZenModel.DataPointGraphPoint' class='DataPointGraphPoint'>
<property select_variable="lineTypes" type="selection" id="lineType" mode="w" >
LINE
</property>
<property type="long" id="lineWidth" mode="w" >
1
</property>
<property type="boolean" id="stacked" mode="w" >
False
</property>
<property type="string" id="format" mode="w" >
%5.2lf%s
</property>
<property type="string" id="legend" mode="w" >
${graphPoint/id}
</property>
<property type="long" id="limit" mode="w" >
-1
</property>
<property type="string" id="dpName" mode="w" >
Varnish3Stats_n_expired
</property>
<property type="string" id="cFunc" mode="w" >
AVERAGE
</property>
</object>
</tomanycont>
</object>
<object id='Varnish3 GZIP Operations' module='Products.ZenModel.GraphDefinition' class='GraphDefinition'>
<property type="int" id="height" mode="w" >
100
</property>
<property type="int" id="width" mode="w" >
500
</property>
<property type="boolean" id="log" mode="w" >
False
</property>
<property type="boolean" id="base" mode="w" >
False
</property>
<property type="int" id="miny" mode="w" >
-1
</property>
<property type="int" id="maxy" mode="w" >
-1
</property>
<property type="boolean" id="hasSummary" mode="w" >
True
</property>
<property type="long" id="sequence" mode="w" >
4
</property>
<tomanycont id='graphPoints'>
<object id='n_gunzip' module='Products.ZenModel.DataPointGraphPoint' class='DataPointGraphPoint'>
<property type="long" id="sequence" mode="w" >
1
</property>
<property select_variable="lineTypes" type="selection" id="lineType" mode="w" >
LINE
</property>
<property type="long" id="lineWidth" mode="w" >
1
</property>
<property type="boolean" id="stacked" mode="w" >
False
</property>
<property type="string" id="format" mode="w" >
%5.2lf%s
</property>
<property type="string" id="legend" mode="w" >
${graphPoint/id}
</property>
<property type="long" id="limit" mode="w" >
-1
</property>
<property type="string" id="dpName" mode="w" >
Varnish3Stats_n_gunzip
</property>
<property type="string" id="cFunc" mode="w" >
AVERAGE
</property>
</object>
<object id='n_gzip' module='Products.ZenModel.DataPointGraphPoint' class='DataPointGraphPoint'>
<property select_variable="lineTypes" type="selection" id="lineType" mode="w" >
LINE
</property>
<property type="long" id="lineWidth" mode="w" >
1
</property>
<property type="boolean" id="stacked" mode="w" >
False
</property>
<property type="string" id="format" mode="w" >
%5.2lf%s
</property>
<property type="string" id="legend" mode="w" >
${graphPoint/id}
</property>
<property type="long" id="limit" mode="w" >
-1
</property>
<property type="string" id="dpName" mode="w" >
Varnish3Stats_n_gzip
</property>
<property type="string" id="cFunc" mode="w" >
AVERAGE
</property>
</object>
</tomanycont>
</object>
</tomanycont>
</object>
</objects>
